README
classgraph.py
setup.py
classgraph.egg-info/PKG-INFO
classgraph.egg-info/SOURCES.txt
classgraph.egg-info/dependency_links.txt
classgraph.egg-info/top_level.txt