Metadata-Version: 1.0
Name: classgraph
Version: 0.1
Summary: Generate a Graphviz diagram of Python classes
Home-page: http://www.issaris.org/
Author: Panagiotis H.M. Issaris
Author-email: takis@issaris.org
License: GPL
Platform: linux
Classifier: Environment :: Console
